statcast_pitches/__init__.py
statcast_pitches/_load_pitches.py
statcast_pitches/_utils.py
statcast_pitches-1.0.0.dist-info/METADATA
statcast_pitches-1.0.0.dist-info/WHEEL
statcast_pitches-1.0.0.dist-info/RECORD
