Metadata-Version: 2.4
Name: statcast_pitches
Version: 1.0.0
Summary: A package for loading MLB Statcast pitch data quickly using HF Dataset
Project-URL: Repository, https://github.com/Jensen-holm/statcast-era-pitches
Project-URL: HuggingFaceDataset, https://huggingface.com/Jensen-holm/statcast-era-pitches
Author-email: Jensen Holm <jensenh87@gmail.com>
License-Expression: MIT
Keywords: baseball,data,mlb,statcast
Requires-Python: >=3.8
Requires-Dist: duckdb
Requires-Dist: polars
Requires-Dist: pyarrow
Provides-Extra: dev
Requires-Dist: build; extra == 'dev'
Requires-Dist: pytest; extra == 'dev'
Requires-Dist: twine; extra == 'dev'
